LICENSE
MANIFEST.in
README.rst
setup.py
django_testlink.egg-info/PKG-INFO
django_testlink.egg-info/SOURCES.txt
django_testlink.egg-info/dependency_links.txt
django_testlink.egg-info/top_level.txt
testlink/__init__.py
testlink/admin.py
testlink/apps.py
testlink/models.py
testlink/tests.py
testlink/views.py
testlink/migrations/__init__.py