Metadata-Version: 1.1
Name: django-testlink
Version: 0.0.1
Summary: A Django app to integrate php testlink 1.9.16 into Django system.
Home-page: https://www.example.com/
Author: Lang Ma
Author-email: malang321@163.com
License: BSD License
Platform: UNKNOWN
Classifier: Environment :: Web Environment
Classifier: Framework :: Django
Classifier: Framework :: Django :: 1.10
Classifier: License :: OSI Approved :: BSD License
Classifier: Programming Language :: Python
Classifier: Programming Language :: Python :: 3.4
Classifier: Programming Language :: Python :: 3.5
Classifier: Topic :: Internet :: WWW/HTTP
Classifier: Topic :: Internet :: WWW/HTTP :: Dynamic Content
